simpandas/__init__.py
simpandas/basics.py
simpandas/errors.py
simpandas/frame.py
simpandas/index.py
simpandas/indexer.py
simpandas/series.py
simpandas/common/_internal_processes.py
simpandas/common/daterelated.py
simpandas/common/filters.py
simpandas/common/helpers.py
simpandas/common/math.py
simpandas/common/merger.py
simpandas/common/renamer.py
simpandas/common/shape.py
simpandas/common/slope.py
simpandas/common/stringformat.py
simpandas/readers/__init__.py
simpandas/readers/xlsx.py
simpandas/writters/__init__.py
simpandas/writters/schedule.py
simpandas/writters/xlsx.py
simpandas-0.83.22.dist-info/LICENSE
simpandas-0.83.22.dist-info/METADATA
simpandas-0.83.22.dist-info/WHEEL
simpandas-0.83.22.dist-info/top_level.txt
simpandas-0.83.22.dist-info/RECORD
