Metadata-Version: 2.1
Name: simpandas
Version: 0.83.22
Summary: a couple of Pandas DataFrame and Series subclasses with extentions to work with units and to deal with column names in eclipse simulator output style.
Author-email: Martin Carlos Araya <martinaraya@gmail.com>
License: GNU GENERAL PUBLIC LICENSE
Project-URL: Homepage, https://github.com/ayaranitram/simpandas
Project-URL: Bug Tracker, https://github.com/ayaranitram/simpandas/issues
Classifier: Programming Language :: Python :: 3
Classifier: License :: OSI Approved :: GNU Affero General Public License v3
Classifier: Operating System :: OS Independent
Requires-Python: >=3.7
License-File: LICENSE
Requires-Dist: numpy
Requires-Dist: pandas
Requires-Dist: matplotlib
Requires-Dist: seaborn
Requires-Dist: datetime
Requires-Dist: unyts (>=0.5.25)
